dafin/__init__.py
dafin/performance.py
dafin/plot.py
dafin/returns_data.py
dafin/utils.py
tests/__init__.py
tests/test_performance.py
tests/test_returns_data.py
tests/utils.py
dafin-0.0.3.dist-info/METADATA
dafin-0.0.3.dist-info/WHEEL
dafin-0.0.3.dist-info/top_level.txt
dafin-0.0.3.dist-info/RECORD
