Metadata-Version: 2.1
Name: dafin
Version: 0.0.3
Summary: Finance Data
Home-page: https://github.com/mkareshk/dafin
Author: Moein Kareshk
Author-email: mkareshk@outlook.com
Classifier: Programming Language :: Python :: 3
Classifier: Operating System :: OS Independent
Requires-Python: >=3.10
Requires-Dist: seaborn
Requires-Dist: yfinance>=0.2.49
Requires-Dist: yfinance[nospam]>=0.2.49
Requires-Dist: requests-cache
Requires-Dist: requests-ratelimiter
Requires-Dist: scipy
Provides-Extra: dev
Requires-Dist: pre-commit; extra == "dev"
Requires-Dist: pytest; extra == "dev"
Requires-Dist: pytest-runner; extra == "dev"
Requires-Dist: pytest-cov; extra == "dev"
Requires-Dist: pylint; extra == "dev"
Requires-Dist: twine; extra == "dev"
